twitch_python_wrapper/__init__.py
twitch_python_wrapper/enums.py
twitch_python_wrapper/objects.py
twitch_python_wrapper/api/__init__.py
twitch_python_wrapper/api/client.py
twitch_python_wrapper/api/enums.py
twitch_python_wrapper/api/objects.py
twitch_python_wrapper/api/endpoint_groups/__init__.py
twitch_python_wrapper/api/endpoint_groups/ads.py
twitch_python_wrapper/api/endpoint_groups/analytics.py
twitch_python_wrapper/api/endpoint_groups/bits.py
twitch_python_wrapper/api/endpoint_groups/ccls.py
twitch_python_wrapper/api/endpoint_groups/channel_points.py
twitch_python_wrapper/api/endpoint_groups/channels.py
twitch_python_wrapper/api/endpoint_groups/charity.py
twitch_python_wrapper/api/endpoint_groups/chat.py
twitch_python_wrapper/api/endpoint_groups/clips.py
twitch_python_wrapper/api/endpoint_groups/conduits.py
twitch_python_wrapper/api/endpoint_groups/entitlements.py
twitch_python_wrapper/api/endpoint_groups/eventsub.py
twitch_python_wrapper/api/endpoint_groups/extensions.py
twitch_python_wrapper/api/endpoint_groups/games.py
twitch_python_wrapper/api/endpoint_groups/goals.py
twitch_python_wrapper/api/endpoint_groups/hype_train.py
twitch_python_wrapper/api/endpoint_groups/moderation.py
twitch_python_wrapper/api/endpoint_groups/polls.py
twitch_python_wrapper/api/endpoint_groups/predictions.py
twitch_python_wrapper/api/endpoint_groups/raids.py
twitch_python_wrapper/api/endpoint_groups/schedule.py
twitch_python_wrapper/api/endpoint_groups/search.py
twitch_python_wrapper/api/endpoint_groups/streams.py
twitch_python_wrapper/api/endpoint_groups/subscriptions.py
twitch_python_wrapper/api/endpoint_groups/teams.py
twitch_python_wrapper/api/endpoint_groups/users.py
twitch_python_wrapper/api/endpoint_groups/videos.py
twitch_python_wrapper/api/endpoint_groups/whispers.py
twitch_python_wrapper/eventsub/__init__.py
twitch_python_wrapper/eventsub/client.py
twitch_python_wrapper/eventsub/enums.py
twitch_python_wrapper/eventsub/objects.py
twitch_python_wrapper-1.0.0b0.dist-info/METADATA
twitch_python_wrapper-1.0.0b0.dist-info/WHEEL
twitch_python_wrapper-1.0.0b0.dist-info/licenses/LICENSE
twitch_python_wrapper-1.0.0b0.dist-info/RECORD
