Metadata-Version: 2.4
Name: twitch-python-wrapper
Version: 1.0.0b0
Summary: A Python wrapper for the Twitch API, EventSub and Authentication
Project-URL: Repository, https://github.com/RLVizgarra/twitch-python-wrapper
Project-URL: Changelog, https://github.com/RLVizgarra/twitch-python-wrapper/blob/main/CHANGELOG.md
Project-URL: Issues, https://github.com/RLVizgarra/twitch-python-wrapper/issues
Author-email: RLVizgarra <rodrigolionvizgarra@gmail.com>
License-Expression: MPL-2.0
License-File: LICENSE
Keywords: api,bot,eventsub,framework,twitch,wrapper
Classifier: Development Status :: 4 - Beta
Classifier: Environment :: No Input/Output (Daemon)
Classifier: Intended Audience :: Developers
Classifier: License :: OSI Approved :: Mozilla Public License 2.0 (MPL 2.0)
Classifier: Operating System :: OS Independent
Classifier: Programming Language :: Python :: 3
Classifier: Programming Language :: Python :: 3 :: Only
Classifier: Programming Language :: Python :: 3.10
Classifier: Programming Language :: Python :: 3.11
Classifier: Programming Language :: Python :: 3.12
Classifier: Programming Language :: Python :: 3.13
Classifier: Programming Language :: Python :: 3.14
Classifier: Topic :: Software Development :: Libraries :: Application Frameworks
Classifier: Typing :: Typed
Requires-Python: >=3.10
Requires-Dist: certifi
Requires-Dist: httpx
Requires-Dist: python-dateutil
Requires-Dist: pytz
Requires-Dist: websockets
